IteratorDecorator/__init__.py
IteratorDecorator/src.py
IteratorDecorator-0.11.dist-info/LICENSE
IteratorDecorator-0.11.dist-info/METADATA
IteratorDecorator-0.11.dist-info/WHEEL
IteratorDecorator-0.11.dist-info/top_level.txt
IteratorDecorator-0.11.dist-info/RECORD
