Metadata-Version: 2.1
Name: IteratorDecorator
Version: 0.11
Summary: Adds dynamically interface of iterator to class
Home-page: https://github.com/stovorov/IteratorDecorator
Author: Pawel Stoworowicz
Author-email: stoworow@gmail.com
License: MIT
Platform: UNKNOWN
